chap/__main__.py
chap/__version__.py
chap/core.py
chap/key.py
chap/py.typed
chap/session.py
chap/backends/anthropic.py
chap/backends/huggingface.py
chap/backends/llama_cpp.py
chap/backends/lorem.py
chap/backends/mistral.py
chap/backends/openai_chatgpt.py
chap/backends/textgen.py
chap/commands/ask.py
chap/commands/cat.py
chap/commands/grep.py
chap/commands/import.py
chap/commands/render.py
chap/commands/tui.css
chap/commands/tui.py
chap-0.8.4.dist-info/METADATA
chap-0.8.4.dist-info/WHEEL
chap-0.8.4.dist-info/entry_points.txt
chap-0.8.4.dist-info/top_level.txt
chap-0.8.4.dist-info/RECORD
