Metadata-Version: 2.1
Name: chap
Version: 0.8.4
Summary: Interact with the OpenAI ChatGPT API (and other text generators)
Author-email: Jeff Epler <jepler@gmail.com>
Project-URL: homepage, https://github.com/jepler/chap
Project-URL: repository, https://github.com/jepler/chap
Keywords: llm,tui,chatgpt
Classifier: Development Status :: 3 - Alpha
Classifier: License :: OSI Approved :: MIT License
Classifier: Operating System :: OS Independent
Classifier: Programming Language :: Python :: 3
Classifier: Programming Language :: Python :: 3.9
Classifier: Programming Language :: Python :: 3.10
Classifier: Programming Language :: Python :: 3.11
Classifier: Programming Language :: Python :: 3.12
Classifier: Programming Language :: Python :: Implementation :: CPython
Classifier: Programming Language :: Python :: Implementation :: PyPy
Requires-Python: >=3.9
Requires-Dist: click
Requires-Dist: httpx
Requires-Dist: lorem-text
Requires-Dist: platformdirs
Requires-Dist: pyperclip
Requires-Dist: simple-parsing
Requires-Dist: textual[syntax]
Requires-Dist: tiktoken
Requires-Dist: websockets
